league_data_mcp/__init__.py
league_data_mcp/utility.py
league_data_mcp-1.0.2.dist-info/WHEEL
league_data_mcp-1.0.2.dist-info/entry_points.txt
league_data_mcp-1.0.2.dist-info/METADATA
league_data_mcp-1.0.2.dist-info/RECORD
