Metadata-Version: 2.3
Name: league-data-mcp
Version: 1.0.2
Summary: A Model Context Protocol (MCP) server that provides access to League of Legends game data through the Riot Games API
Keywords: mcp,league-of-legends,riot-games
Author: Yuyang Shi
License: MIT
Requires-Dist: mcp[cli]>=1.13.1
Requires-Dist: requests>=2.32.5
Maintainer: Yuyang Shi
Requires-Python: >=3.13
